{"exam_board":"WAEC GCE","subject":"Literature in English","year":"2026","syllabus_url":"https://www.waeconline.org.ng/","modules":[{"id":"genres","title":"Literary Genres","weight_in_exam":25,"topics":[{"id":"prose","title":"Prose Fiction","examination_focus":["Plot structure: exposition, climax, resolution","Characterization: flat, round, static, dynamic","Narrative point of view","Setting as a literary device","Theme and subject matter"],"past_question_years":["2023","2024","2025"],"typical_question_style":"discuss the narrative technique in the passage","difficulty_rating":"medium"},{"id":"drama","title":"Drama","examination_focus":["Elements of drama: plot, character, dialogue","Types of drama: tragedy, comedy, tragicomedy","Stagecraft and dramatic techniques","Conflict and character motivation","Use of soliloquy and aside"],"past_question_years":["2023","2024","2025"],"typical_question_style":"identify dramatic techniques in the scene","difficulty_rating":"medium"},{"id":"poetry","title":"Poetry","examination_focus":["Rhyme, rhythm and meter","Poetic devices: simile, metaphor, personification","Imagery and symbolism","Stanza forms and structure","Theme and tone in poetry"],"past_question_years":["2023","2024","2025"],"typical_question_style":"discuss the use of imagery in the poem","difficulty_rating":"medium"}]},{"id":"criticism","title":"Literary Appreciation and Criticism","weight_in_exam":15,"topics":[{"id":"appreciation","title":"Literary Appreciation Skills","examination_focus":["Critical analysis of unseen passages","Identification of literary devices","Commenting on style and diction","Theme extraction and analysis","Comparison of texts"],"past_question_years":["2023","2024","2025"],"typical_question_style":"write critical appreciation of the given poem","difficulty_rating":"hard"}]},{"id":"african","title":"African Literature","weight_in_exam":30,"topics":[{"id":"african_prose","title":"African Prose","examination_focus":["Recommended novels and their contexts","Themes: tradition vs change, colonialism","Character and society interplay","Narrative techniques in African fiction","Language and style"],"past_question_years":["2023","2024","2025"],"typical_question_style":"discuss the theme of cultural conflict in the novel","difficulty_rating":"medium"},{"id":"african_drama","title":"African Drama","examination_focus":["Recommended plays and their themes","Ritual and performance","Political and social commentary","Characterization and symbolism","Language and stage directions"],"past_question_years":["2023","2024","2025"],"typical_question_style":"analyze the role of the protagonist in the play","difficulty_rating":"medium"},{"id":"african_poetry","title":"African Poetry","examination_focus":["Recommended poems and contexts","Oral tradition influences","Themes: identity, liberation, culture","Imagery and symbolism","Poetic form and rhythm"],"past_question_years":["2023","2024","2025"],"typical_question_style":"discuss the theme of liberation in the poem","difficulty_rating":"hard"}]},{"id":"non_african","title":"Non-African Literature","weight_in_exam":30,"topics":[{"id":"non_african_prose","title":"Non-African Prose","examination_focus":["Recommended novels: themes and contexts","Characterization and psychological depth","Social and historical background","Narrative innovation and techniques","Symbolism and motif"],"past_question_years":["2023","2024","2025"],"typical_question_style":"discuss the theme of love in the novel","difficulty_rating":"medium"},{"id":"non_african_drama","title":"Non-African Drama","examination_focus":["Recommended plays: themes and styles","Shakespearean conventions","Modern dramatic techniques","Dramatic irony and suspense","Social criticism in drama"],"past_question_years":["2023","2024","2025"],"typical_question_style":"explain the use of dramatic irony in the play","difficulty_rating":"medium"},{"id":"non_african_poetry","title":"Non-African Poetry","examination_focus":["Recommended poems: themes and forms","Romantic and Victorian poetry","Modernist and contemporary poetry","Figurative language and imagery","Verse forms and innovation"],"past_question_years":["2023","2024","2025"],"typical_question_style":"compare the treatment of nature in two poems","difficulty_rating":"hard"}]}]}