{"exam_board":"NECO","subject":"Physics","year":"2026","syllabus_url":"https://neco.gov.ng/","modules":[{"id":"mechanics","title":"Mechanics","weight_in_exam":30,"topics":[{"id":"motion","title":"Motion and Gravitation","examination_focus":["Linear motion equations","Projectiles","Newton's laws of motion","Conservation principles","Gravitational field"],"past_question_years":["2023","2024","2025"],"typical_question_style":"calculate range and maximum height of projectile","difficulty_rating":"medium"},{"id":"energy","title":"Work, Energy and Power","examination_focus":["Work done by constant and variable forces","Kinetic and potential energy","Power and efficiency","Energy conservation","Mechanical advantage"],"past_question_years":["2023","2024","2025"],"typical_question_style":"calculate efficiency of a simple machine","difficulty_rating":"medium"}]},{"id":"waves","title":"Waves","weight_in_exam":25,"topics":[{"id":"wave_motion","title":"Wave Motion","examination_focus":["Types of waves","Wave equation","Superposition principle","Standing waves","Resonance"],"past_question_years":["2023","2024","2025"],"typical_question_style":"calculate frequency of vibrating string","difficulty_rating":"medium"},{"id":"optics","title":"Geometric and Physical Optics","examination_focus":["Reflection and refraction","Lens formula and magnification","Optical instruments","Diffraction grating","Polarization of light"],"past_question_years":["2023","2024","2025"],"typical_question_style":"calculate image distance using mirror formula","difficulty_rating":"medium"}]},{"id":"electricity","title":"Electricity and Magnetism","weight_in_exam":25,"topics":[{"id":"electrostatics","title":"Electrostatics","examination_focus":["Coulomb's law","Electric field intensity","Electric potential","Capacitors","Energy stored in capacitor"],"past_question_years":["2023","2024","2025"],"typical_question_style":"calculate force between two charges","difficulty_rating":"medium"},{"id":"current","title":"Current Electricity","examination_focus":["Ohm's law and resistivity","Electromotive force","Internal resistance","Kirchhoff's laws","Electrical measurements"],"past_question_years":["2023","2024","2025"],"typical_question_style":"calculate current in complex circuit using Kirchhoff's laws","difficulty_rating":"hard"}]},{"id":"modern","title":"Modern and Nuclear Physics","weight_in_exam":20,"topics":[{"id":"atomic","title":"Atomic Physics","examination_focus":["Models of the atom","Energy levels","Photoelectric effect","X-rays","Wave-particle duality"],"past_question_years":["2023","2024","2025"],"typical_question_style":"calculate energy of photon given wavelength","difficulty_rating":"hard"},{"id":"nuclear","title":"Nuclear Physics","examination_focus":["Radioactive decay","Half-life calculations","Nuclear reactions","Binding energy","Applications and safety"],"past_question_years":["2023","2024","2025"],"typical_question_style":"calculate binding energy per nucleon","difficulty_rating":"hard"}]}]}